LICENSE
MANIFEST.in
README.md
pyproject.toml
requirements.txt
setup.py
.pytest_cache/README.md
benchmarks/README.md
integer_programming/VERSION
integer_programming/__init__.py
integer_programming/steinitz.py
integer_programming.egg-info/PKG-INFO
integer_programming.egg-info/SOURCES.txt
integer_programming.egg-info/dependency_links.txt
integer_programming.egg-info/requires.txt
integer_programming.egg-info/top_level.txt