Metadata-Version: 2.1
Name: integer-programming
Version: 0.7.1
Summary: Integer programming in Python
Home-page: https://github.com/SamuelBismuth/integer_programming
Author: Samuel Bismuth
Author-email: samuelbimsuth@101gmail.com
License: MIT
Project-URL: Bug Reports, https://github.com/SamuelBismuth/integer_programming/issues
Project-URL: Source Code, https://github.com/SamuelBismuth/integer_programming
Keywords: optimization
Platform: UNKNOWN
Classifier: Development Status :: 2 - Pre-Alpha
Requires-Python: >=3.8
License-File: LICENSE
